haconiwa/__init__.py
haconiwa/__main__.py
haconiwa/cli.py
haconiwa/agent/__init__.py
haconiwa/agent/base.py
haconiwa/agent/boss.py
haconiwa/agent/claude_integration.py
haconiwa/agent/cli.py
haconiwa/agent/manager.py
haconiwa/agent/worker.py
haconiwa/core/__init__.py
haconiwa/core/applier.py
haconiwa/core/cli.py
haconiwa/core/config.py
haconiwa/core/logging.py
haconiwa/core/state.py
haconiwa/core/upgrade.py
haconiwa/core/crd/__init__.py
haconiwa/core/crd/models.py
haconiwa/core/crd/parser.py
haconiwa/core/policy/__init__.py
haconiwa/core/policy/engine.py
haconiwa/core/policy/validator.py
haconiwa/legal/__init__.py
haconiwa/legal/framework.py
haconiwa/monitor/__init__.py
haconiwa/monitor/tmux_monitor.py
haconiwa/organization/__init__.py
haconiwa/organization/manager.py
haconiwa/resource/__init__.py
haconiwa/resource/cli.py
haconiwa/resource/db_fetcher.py
haconiwa/resource/path_scanner.py
haconiwa/scan/__init__.py
haconiwa/scan/analyzer.py
haconiwa/scan/cli.py
haconiwa/scan/comparator.py
haconiwa/scan/formatter.py
haconiwa/scan/generate_parallel.py
haconiwa/scan/guide_generator.py
haconiwa/scan/scanner.py
haconiwa/scripts/__init__.py
haconiwa/scripts/prerelease.py
haconiwa/scripts/test_runner.py
haconiwa/space/__init__.py
haconiwa/space/cli.py
haconiwa/space/manager.py
haconiwa/space/tmux.py
haconiwa/task/__init__.py
haconiwa/task/cli.py
haconiwa/task/manager.py
haconiwa/task/submit.py
haconiwa/task/worktree.py
haconiwa/tool/__init__.py
haconiwa/tool/parallel_dev.py
haconiwa/tool/parallel_dev_simple.py
haconiwa/utils/__init__.py
haconiwa/utils/typer_ext.py
haconiwa/watch/__init__.py
haconiwa/watch/cli.py
haconiwa/watch/monitor.py
haconiwa/world/__init__.py
haconiwa/world/cli.py
haconiwa/world/provider/__init__.py
haconiwa/world/provider/docker.py
haconiwa/world/provider/local.py
haconiwa-0.6.3.dist-info/licenses/LICENSE
haconiwa-0.6.3.dist-info/METADATA
haconiwa-0.6.3.dist-info/WHEEL
haconiwa-0.6.3.dist-info/entry_points.txt
haconiwa-0.6.3.dist-info/top_level.txt
haconiwa-0.6.3.dist-info/RECORD
