Metadata-Version: 2.4
Name: haconiwa
Version: 0.6.3
Summary: AI協調開発支援Python CLIツール - 箱庭での開発を支援
Author-email: Daisuke Motoki <kanri@kandaquantum.co.jp>
Project-URL: Homepage, https://github.com/haconiwa/haconiwa
Project-URL: Documentation, https://haconiwa.readthedocs.io
Project-URL: Repository, https://github.com/haconiwa/haconiwa.git
Project-URL: Issues, https://github.com/haconiwa/haconiwa/issues
Classifier: Development Status :: 3 - Alpha
Classifier: Environment :: Console
Classifier: Intended Audience :: Developers
Classifier: Operating System :: OS Independent
Classifier: Programming Language :: Python :: 3.10
Classifier: Programming Language :: Python :: 3.11
Classifier: Programming Language :: Python :: 3.12
Classifier: Topic :: Software Development :: Libraries :: Python Modules
Requires-Python: >=3.10
License-File: LICENSE
Requires-Dist: typer>=0.9.0
Requires-Dist: libtmux>=0.23.2
Requires-Dist: gitpython>=3.1.40
Requires-Dist: prometheus-client>=0.17.1
Requires-Dist: pyyaml>=6.0.1
Requires-Dist: rich>=13.7.0
Requires-Dist: click>=8.1.7
Requires-Dist: pydantic>=2.0.0
Requires-Dist: claude-code-sdk>=0.0.10
Requires-Dist: psutil>=5.9.0
Requires-Dist: anyio>=3.7.0
Requires-Dist: python-dotenv>=1.0.0
Requires-Dist: watchdog>=3.0.0
Requires-Dist: cryptography>=3.0.0
Requires-Dist: pandas>=1.0.0
Requires-Dist: matplotlib>=3.0.0
Requires-Dist: sqlalchemy>=1.4.0
Requires-Dist: packaging>=20.0
Provides-Extra: docker
Requires-Dist: docker>=6.1.3; extra == "docker"
Provides-Extra: dev
Requires-Dist: pytest>=7.4.3; extra == "dev"
Requires-Dist: pytest-cov>=4.1.0; extra == "dev"
Requires-Dist: black>=23.11.0; extra == "dev"
Requires-Dist: flake8>=6.1.0; extra == "dev"
Requires-Dist: mypy>=1.7.1; extra == "dev"
Requires-Dist: bandit>=1.7.5; extra == "dev"
Requires-Dist: isort>=5.12.0; extra == "dev"
Requires-Dist: pre-commit>=3.5.0; extra == "dev"
Dynamic: license-file
